{
    "cardName": "Litwick",
    "cardId": "litwick_1",
    "imageName": "litwick_1.png",
    "cardType": "Pokemon",
    "deckCardId": 92,
    "stage": 0,
    "evolvesFrom": "",
    "hp": 90,
    "type": "Fire",
    "retreatCost": 1,
    "attacks": [
        {
            "attackName": "Rekindle",
            "damage": 10,
            "attackDescription": "Take 1 Energy and put it on 1 of your Benched Pokemon.",
            "attackCost": [
                "Colorless"
            ],
            "effects": [
                {
                    "cardEffectType": "EnergyRamp",
                    "cardEffectTarget": "BenchPokemon",
                    "effectAmount": 1
                }
            ]
        }
    ]
}